rabbot/__init__.py
rabbot/__main__.py
rabbot/__version__.py
rabbot/cli.py
rabbot/commands/__init__.py
rabbot/commands/cmd_check.py
rabbot/commands/cmd_version.py
rabbot-0.3.4.dist-info/entry_points.txt
rabbot-0.3.4.dist-info/WHEEL
rabbot-0.3.4.dist-info/METADATA
rabbot-0.3.4.dist-info/RECORD
