Metadata-Version: 2.1
Name: rabbot
Version: 0.3.4
Summary: A small utility for testing RabbitMQ connections.
Home-page: https://github.com/dsudduth/rabbot
License: MIT
Keywords: tools,rabbitmq
Author: Derek Sudduth
Author-email: derek.sudduth@gmail.com
Requires-Python: >=3.7,<4.0
Classifier: Development Status :: 5 - Production/Stable
Classifier: Environment :: Console
Classifier: Intended Audience :: Developers
Classifier: License :: OSI Approved :: MIT License
Classifier: Operating System :: OS Independent
Classifier: Programming Language :: Python :: 3
Classifier: Programming Language :: Python :: 3.7
Classifier: Topic :: Software Development :: Build Tools
Classifier: Topic :: Software Development :: Libraries :: Python Modules
Requires-Dist: pika (>=1.1,<2.0)
Project-URL: Repository, https://github.com/dsudduth/rabbot
